MANIFEST.in
README.md
setup.py
juegosseries.egg-info/PKG-INFO
juegosseries.egg-info/SOURCES.txt
juegosseries.egg-info/dependency_links.txt
juegosseries.egg-info/top_level.txt
seriesjuegos/Entregable.py
seriesjuegos/Serie.py
seriesjuegos/Videojuego.py
seriesjuegos/__init__.py