Metadata-Version: 1.1
Name: juegosseries
Version: 0.3
Summary: Academic Project
Home-page: https://github.com/Gabrinev/seriesjuegos
Author: GN
Author-email: ranamarrana@gmail.com
License: LGPL v3
Download-URL: https://github.com/Gabrinev/seriesjuegos/archive/refs/heads/master.zip
Keywords: python objects games series
Platform: UNKNOWN
Classifier: Programming Language :: Python
Classifier: Programming Language :: Python :: 2.7
Classifier: Programming Language :: Python :: 3.3
Classifier: Programming Language :: Python :: 3.4
Classifier: Programming Language :: Python :: 3.5
Classifier: Programming Language :: Python :: 3.6
Classifier: Programming Language :: Python :: 3.7
